mockrdd/__init__.py
mockrdd-0.0.2.dist-info/METADATA
mockrdd-0.0.2.dist-info/RECORD
mockrdd-0.0.2.dist-info/WHEEL
mockrdd-0.0.2.dist-info/top_level.txt
