Metadata-Version: 2.1
Name: mockrdd
Version: 0.0.2
Summary: Utility for testing PySpark code
Home-page: https://github.com/LiveRamp/mockrdd
Author: Matt Hagy
Author-email: matt@liveramp.com
License: UNKNOWN
Platform: UNKNOWN
Classifier: Programming Language :: Python :: 3
Classifier: License :: OSI Approved :: MIT License
Classifier: Operating System :: OS Independent
